{
    "Name":  "LinkedIn Service",
    "Type":  "LinkedInPage",
    "About":  "The LinkedIn service allows you to connect to retrieve or publish data to LinkedIn.",
    "CodeUrl":  "https://github.com/Microsoft/UWPCommunityToolkit/tree/master/Microsoft.Toolkit.Uwp.Services/Services/LinkedIn/",
    "CodeFile":  "LinkedInCode.code",
    "Icon":  "/SamplePages/LinkedIn Service/LinkedInLogo.png",
    "DocumentationUrl":  "https://raw.githubusercontent.com/Microsoft/UWPCommunityToolkit/master/docs/services/Linkedin.md",
    "Category":  "Services"
}